heerlijke_lib/__init__.py
heerlijke_lib/datastructures/__init__.py
heerlijke_lib/datastructures/case_insensitive_strenum.py
heerlijke_lib-0.1.4.dist-info/METADATA
heerlijke_lib-0.1.4.dist-info/WHEEL
heerlijke_lib-0.1.4.dist-info/licenses/LICENSE.txt
heerlijke_lib-0.1.4.dist-info/RECORD
