Metadata-Version: 2.1
Name: heerlijke-lib
Version: 0.1.4
Summary: Library of personal utilities.
Author-email: Thomas Vanhelden <thomas.vanhelden@gmail.com>
License: MIT
License-File: LICENSE.txt
Requires-Python: >=3.10
Requires-Dist: strenum==0.4.15
